Metadata-Version: 2.1
Name: rhasspy-asr-kaldi-hermes
Version: 0.7.1
Summary: UNKNOWN
Home-page: https://github.com/rhasspy/rhasspy-asr-kaldi-hermes
Author: Michael Hansen
Author-email: mike@rhasspy.org
License: UNKNOWN
Platform: UNKNOWN
Classifier: Programming Language :: Python :: 3
Classifier: License :: OSI Approved :: MIT License
Requires-Python: >=3.7
